calkit/__init__.py
calkit/__main__.py
calkit/calc.py
calkit/check.py
calkit/cloud.py
calkit/conda.py
calkit/config.py
calkit/core.py
calkit/datasets.py
calkit/docker.py
calkit/dvc.py
calkit/environments.py
calkit/git.py
calkit/github.py
calkit/gui.py
calkit/invenio.py
calkit/jupyter.py
calkit/licenses.py
calkit/magics.py
calkit/matlab.py
calkit/notebooks.py
calkit/office.py
calkit/ops.py
calkit/overleaf.py
calkit/pipeline.py
calkit/releases.py
calkit/server.py
calkit/cli/__init__.py
calkit/cli/check.py
calkit/cli/cloud.py
calkit/cli/config.py
calkit/cli/core.py
calkit/cli/describe.py
calkit/cli/import_.py
calkit/cli/latex.py
calkit/cli/list.py
calkit/cli/main.py
calkit/cli/new.py
calkit/cli/notebooks.py
calkit/cli/office.py
calkit/cli/overleaf.py
calkit/cli/slurm.py
calkit/cli/update.py
calkit/jupyterlab/__init__.py
calkit/jupyterlab/routes.py
calkit/models/__init__.py
calkit/models/core.py
calkit/models/io.py
calkit/models/iteration.py
calkit/models/pipeline.py
calkit/templates/__init__.py
calkit/templates/core.py
calkit/templates/latex/__init__.py
calkit/templates/latex/core.py
calkit/templates/latex/article/paper.tex
calkit/templates/latex/jfm/jfm.bst
calkit/templates/latex/jfm/jfm.cls
calkit/templates/latex/jfm/lineno-FLM.sty
calkit/templates/latex/jfm/paper.tex
calkit/templates/latex/jfm/upmath.sty
calkit/tests/__init__.py
calkit/tests/test_calc.py
calkit/tests/test_check.py
calkit/tests/test_conda.py
calkit/tests/test_core.py
calkit/tests/test_dvc.py
calkit/tests/test_environments.py
calkit/tests/test_git.py
calkit/tests/test_invenio.py
calkit/tests/test_jupyter.py
calkit/tests/test_magics.py
calkit/tests/test_notebooks.py
calkit/tests/test_pipeline.py
calkit/tests/test_templates.py
calkit/tests/cli/__init__.py
calkit/tests/cli/test_check.py
calkit/tests/cli/test_config.py
calkit/tests/cli/test_import.py
calkit/tests/cli/test_latex.py
calkit/tests/cli/test_list.py
calkit/tests/cli/test_main.py
calkit/tests/cli/test_new.py
calkit/tests/cli/test_notebooks.py
calkit_python-0.33.3.dist-info/METADATA
calkit_python-0.33.3.dist-info/WHEEL
calkit_python-0.33.3.dist-info/entry_points.txt
calkit_python-0.33.3.dist-info/licenses/LICENSE
calkit_python-0.33.3.dist-info/RECORD
