Metadata-Version: 2.4
Name: calkit-python
Version: 0.33.3
Summary: Reproducibility simplified.
Project-URL: Homepage, https://calkit.org
Project-URL: Issues, https://github.com/calkit/calkit/issues
Project-URL: Repository, https://github.com/calkit/calkit
Author-email: Pete Bachant <petebachant@gmail.com>
License-File: LICENSE
Classifier: Framework :: Jupyter
Classifier: Framework :: Jupyter :: JupyterLab
Classifier: Framework :: Jupyter :: JupyterLab :: 4
Classifier: Framework :: Jupyter :: JupyterLab :: Extensions
Classifier: Framework :: Jupyter :: JupyterLab :: Extensions :: Prebuilt
Classifier: License :: OSI Approved :: MIT License
Classifier: Operating System :: OS Independent
Classifier: Programming Language :: Python
Classifier: Programming Language :: Python :: 3
Classifier: Programming Language :: Python :: 3.10
Classifier: Programming Language :: Python :: 3.11
Classifier: Programming Language :: Python :: 3.12
Classifier: Programming Language :: Python :: 3.13
Classifier: Programming Language :: Python :: 3.14
Requires-Python: >=3.10
Requires-Dist: arithmeval
Requires-Dist: bibtexparser
Requires-Dist: checksumdir
Requires-Dist: docx2pdf
Requires-Dist: dvc==3.64.2
Requires-Dist: fastapi
Requires-Dist: gitpython
Requires-Dist: json2latex>=0.0.3
Requires-Dist: jupyterlab>=4.4.5
Requires-Dist: keyring
Requires-Dist: nbconvert
Requires-Dist: papermill>=2.6.0
Requires-Dist: pathspec<1.0.0
Requires-Dist: pillow
Requires-Dist: psutil>=7.0.0
Requires-Dist: pydantic-settings
Requires-Dist: pydantic[email]
Requires-Dist: pyjwt
Requires-Dist: python-dotenv>=1
Requires-Dist: pywin32; platform_system == 'Windows'
Requires-Dist: requests
Requires-Dist: sqlitedict>=2.1.0
Requires-Dist: tqdm>=4.67.1
Requires-Dist: typer==0.21.1
Requires-Dist: uvicorn
Provides-Extra: data
Requires-Dist: pandas>=2.2.3; extra == 'data'
Requires-Dist: polars>=1.18.0; extra == 'data'
